octave_sdk/__init__.py
octave_sdk/_client_request_builder.py
octave_sdk/_default_identity.py
octave_sdk/_errors.py
octave_sdk/_octave_client.py
octave_sdk/batch.py
octave_sdk/conflict_exceptions.py
octave_sdk/conflict_manager.py
octave_sdk/connectivity/__init__.py
octave_sdk/connectivity/connectivity.py
octave_sdk/connectivity/connectivity_filter.py
octave_sdk/connectivity/connectivity_util.py
octave_sdk/connectivity/connectivity_util_private.py
octave_sdk/connectivity/exceptions.py
octave_sdk/grpc/quantummachines/__init__.py
octave_sdk/grpc/quantummachines/octave/__init__.py
octave_sdk/grpc/quantummachines/octave/api/__init__.py
octave_sdk/grpc/quantummachines/octave/api/v1/__init__.py
octave_sdk/health_client.py
octave_sdk/health_monitor.py
octave_sdk/octave.py
octave_sdk/octave_async_thread.py
octave_sdk/octave_module_com.py
octave_sdk/singleton.py
qm_octave-2.1.6.dist-info/LICENSE
qm_octave-2.1.6.dist-info/METADATA
qm_octave-2.1.6.dist-info/WHEEL
qm_octave-2.1.6.dist-info/RECORD
