Metadata-Version: 2.3
Name: qm-octave
Version: 2.1.6
Summary: SDK to control an Octave with QUA
License: BSD-3-Clause
Author: QM
Author-email: info@quantum-machines.co
Requires-Python: >=3.9,<3.13
Classifier: License :: OSI Approved :: BSD License
Classifier: Programming Language :: Python :: 3
Classifier: Programming Language :: Python :: 3.9
Classifier: Programming Language :: Python :: 3.10
Classifier: Programming Language :: Python :: 3.11
Classifier: Programming Language :: Python :: 3.12
Requires-Dist: betterproto (==2.0.0b7)
Requires-Dist: grpcio (>=1.59.2,<2.0.0)
Requires-Dist: grpclib (>=0.4.3rc3,<0.5.0) ; python_version >= "3.10" and python_version < "4.0"
Requires-Dist: protobuf (>=4.24,<7)
